odoo/addons/repair_substate/README.rst
odoo/addons/repair_substate/__init__.py
odoo/addons/repair_substate/__manifest__.py
odoo/addons/repair_substate/data/repair_substate_data.xml
odoo/addons/repair_substate/i18n/it.po
odoo/addons/repair_substate/i18n/repair_substate.pot
odoo/addons/repair_substate/models/__init__.py
odoo/addons/repair_substate/models/repair_order.py
odoo/addons/repair_substate/readme/CONTRIBUTORS.md
odoo/addons/repair_substate/readme/DESCRIPTION.md
odoo/addons/repair_substate/readme/USAGE.md
odoo/addons/repair_substate/static/description/icon.png
odoo/addons/repair_substate/static/description/index.html
odoo/addons/repair_substate/views/repair_views.xml
odoo_addon_repair_substate-17.0.1.0.0.3.dist-info/METADATA
odoo_addon_repair_substate-17.0.1.0.0.3.dist-info/WHEEL
odoo_addon_repair_substate-17.0.1.0.0.3.dist-info/top_level.txt
odoo_addon_repair_substate-17.0.1.0.0.3.dist-info/RECORD
