Metadata-Version: 2.1
Name: odoo-addon-repair_substate
Version: 17.0.1.0.0.3
Requires-Python: >=3.10
Requires-Dist: odoo-addon-base_substate>=17.0dev,<17.1dev
Requires-Dist: odoo>=17.0a,<17.1dev
Summary: Repair Sub State
Home-page: https://github.com/OCA/repair
License: AGPL-3
Author: 360ERP, Odoo Community Association (OCA)
Author-email: support@odoo-community.org
Classifier: Programming Language :: Python
Classifier: Framework :: Odoo
Classifier: Framework :: Odoo :: 17.0
Classifier: License :: OSI Approved :: GNU Affero General Public License v3
